cdiserrors.py
cdiserrors-1.0.0.dist-info/LICENSE
cdiserrors-1.0.0.dist-info/WHEEL
cdiserrors-1.0.0.dist-info/METADATA
cdiserrors-1.0.0.dist-info/RECORD
